sconfig/__init__.py
sconfig-0.0.2.dist-info/METADATA
sconfig-0.0.2.dist-info/RECORD
sconfig-0.0.2.dist-info/WHEEL
sconfig-0.0.2.dist-info/top_level.txt
